{
  "animatorMap": {
    "COMMENT": "BigMath",

    // BORROW_AG (meta)
    // (node_ref) is a reference to the content of the nodes
    // (advance) has instructions on how to advance
    // (meta) is about design decisions
    "bigmath": {

      "type": "ANIMATOR",
      "title": "BigMath",
      "COMMENT": "BigMath",
      "version": "1.0.0",
      "rootnode": "INTRO",

      "queueMap": {

        "COMMENT": "@@@@@ CQueues @@@@@",

        "INPUT_HESITATION_FEEDBACK": {
          "type": "QUEUE",
          "reuse": true,
          "COMMENT": "provide feedback for what to do",
          "preenter": [],
          "tracks": [
            // each of these is a PointAndSpeak combination

            // PointAndSpeak
            {"type": "QUEUEDCOMMAND", "id": "SBigMath", "method": "pointAtDotContainer", "parms": "opA:String|one:String", "features": "FTR_ON_DIGIT_ONE&FTR_TAP_CONCRETE"},
            {"type": "QUEUEDAUDIO", "command": "PLAY", "soundsource": "Touch each one to add them up.mp3", "soundpackage":"bigmath", "volume": 1.0, "mode":"flow", "features": "FTR_ON_DIGIT_ONE&FTR_ADDITION&FTR_TAP_CONCRETE"},
            {"type": "QUEUEDAUDIO", "command": "PLAY", "soundsource": "Touch each one to take them away.mp3", "soundpackage":"bigmath", "volume": 1.0, "mode":"flow", "features": "FTR_ON_DIGIT_ONE&FTR_SUBTRACTION&FTR_TAP_CONCRETE"},

            // PointAndSpeak
            {"type": "QUEUEDCOMMAND", "id": "SBigMath", "method": "pointAtDotContainer", "parms": "opA:String|ten:String", "features": "FTR_ON_DIGIT_ONE&FTR_TAP_TO_BORROW"},
            {"type": "QUEUEDAUDIO", "command": "PLAY", "soundsource": "Tap here to borrow a ten.mp3", "soundpackage":"bigmath", "volume": 1.0, "mode":"flow", "features": "FTR_ON_DIGIT_ONE&FTR_TAP_TO_BORROW"},

            // PointAndSpeak
            {"type": "QUEUEDCOMMAND", "id": "SBigMath", "method": "pointAtDigitInput", "parms": "result:String|one:String", "features": "FTR_ON_DIGIT_ONE&FTR_WRITE_DIGIT"},
            {"type": "QUEUEDAUDIO", "command": "PLAY", "soundsource": "Please tap on the box and write your answer.mp3",  "soundpackage":"bigmath", "volume": 1.0, "mode":"flow", "features": "FTR_ON_DIGIT_ONE&FTR_WRITE_DIGIT"},

            // PointAndSpeak
            {"type": "QUEUEDCOMMAND", "id": "SBigMath", "method": "pointAtDotContainer", "parms": "opA:String|ten:String", "features": "FTR_ON_DIGIT_TEN&FTR_TAP_CONCRETE"},
            {"type": "QUEUEDAUDIO", "command": "PLAY", "soundsource": "Touch each ten to add them up.mp3", "soundpackage":"bigmath", "volume": 1.0, "mode":"flow", "features": "FTR_ON_DIGIT_TEN&FTR_ADDITION&FTR_TAP_CONCRETE"},
            {"type": "QUEUEDAUDIO", "command": "PLAY", "soundsource": "Touch each ten to take them away.mp3", "soundpackage":"bigmath", "volume": 1.0, "mode":"flow", "features": "FTR_ON_DIGIT_TEN&FTR_SUBTRACTION&FTR_TAP_CONCRETE"},

            // PointAndSpeak
            {"type": "QUEUEDCOMMAND", "id": "SBigMath", "method": "pointAtDigitInput", "parms": "result:String|ten:String", "features": "FTR_ON_DIGIT_TEN&FTR_WRITE_DIGIT"},
            {"type": "QUEUEDAUDIO", "command": "PLAY", "soundsource": "Please tap on the box and write your answer.mp3",  "soundpackage":"bigmath", "volume": 1.0, "mode":"flow", "features": "FTR_ON_DIGIT_TEN&FTR_WRITE_DIGIT"},

            // PointAndSpeak
            {"type": "QUEUEDCOMMAND", "id": "SBigMath", "method": "pointAtDigitInput", "parms": "result:String|ten:String", "features": "FTR_ON_DIGIT_TONE&FTR_BORROW_ONES"},
            {"type": "QUEUEDAUDIO", "command": "PLAY", "soundsource": "Tap here to borrow a ten.mp3",  "soundpackage":"bigmath", "volume": 1.0, "mode":"flow", "features": "FTR_ON_DIGIT_TEN&FTR_BORROW_ONES"},


            {"type": "QUEUEDCOMMAND", "id": "SBigMath", "method": "triggerHesitationTimer", "parms": "ihf:String"}
          ]
        },

        "NOT_ENOUGH_ONES_B": {
          "type": "QUEUE",
          "reuse": true,
          "COMMENT": "audio feedback for when you don't have enough ones",
          "preenter": [],
          "tracks": [
            {"name": "CANCEL_TIMER", "type": "QUEUEDCOMMAND", "id": "SBigMath", "method": "cancelHesitationTimer", "features":""},
            {"type": "QUEUEDAUDIO", "command": "PLAY", "soundsource": "We dont have enough ones.mp3",  "soundpackage":"bigmath", "volume": 1.0, "mode":"flow", "features": "FTR_ON_DIGIT_ONE"},
            {"type": "QUEUEDAUDIO", "command": "PLAY", "soundsource": "Where can we find more ones.mp3",  "soundpackage":"bigmath", "volume": 1.0, "mode":"flow", "features": "FTR_ON_DIGIT_ONE"},
            {"type": "QUEUEDCOMMAND", "id": "SBigMath", "method": "triggerHesitationTimer", "parms": "not_enough_ones:String"}

          ]
        }
      },

      "nodeMap": {

        "COMMENT": "@@@@@  CNodes  @@@@@",

        "INTRO": {
          "type": "NODE",
          "COMMENT": "Intro Clip - we only ever visit this node once",
          "maptype":"moduleMap",
          "mapname": "INTRO",
          "preenter": ["SET_VERSION"],
          "preexit": [],
          "edges": [
            {
              "constraint": "",
              "edge": "NEXT_PROBLEM"
            }
          ]
        },

        "NEXT_PROBLEM": {
          "type": "NODE",
          "COMMENT": "This node presents the next problem in the data source.",
          "maptype":"moduleMap",
          "mapname": "NEXTPROBLEM",
          "preenter": [],
          "preexit": [],
          "edges": [
            {"constraint": "FTR_IS_CARRY", "edge": "BEGIN_PROBLEM_CARRY"},
            {"constraint": "FTR_IS_BORROW", "edge": "BEGIN_PROBLEM_BORROW"},
            {"constraint": "", "edge": "BEGIN_PROBLEM_REGULAR"}
          ]
        },

        // ==========================
        // ====== BEGIN REGULAR======
        // ==========================

        "BEGIN_PROBLEM_REGULAR": {
          "type": "NODE",
          "COMMENT": "Regular problem with no carry or borrow.",
          "maptype":"moduleMap",
          "mapname": "EMPTY",
          "preenter": [],
          "preexit": [],
          "edges": [
            {"constraint": "", "edge": "NEXT_DIGIT_R"}
          ]
        },

        "NEXT_DIGIT_R":{
          "COMMENT":"This node moves to the next digit in the problem.",
          "type":"node",
          "maptype":"moduleMap",
          "mapname": "NEXTDIGIT",
          "preenter":[],
          "preexit" :[],
          "edges":
          [
            {"constraint":"","edge":"USER_INPUT_R"}
          ]
        },

        "USER_INPUT_R": {
          "COMMENT":"Preps the tutor for user input, then waits for user input.",
          "type": "node",
          "maptype":"moduleMap",
          "mapname": "USERINPUT",
          "preenter": [],
          "preexit": [],
          "edges": [
            {"constraint": "FTR_CORRECT", "edge": "CORRECT_FEEDBACK_R"},
            {"constraint": "", "edge": "WRONG_FEEDBACK_R"}
          ]
        },

        "CORRECT_FEEDBACK_R": {
          "COMMENT": "Provides feedback for correct response.",
          "type": "node",
          "maptype": "moduleMap",
          "mapname": "CORRECTFEEDBACK",
          "preenter": [],
          "preexit": [],
          "edges": [
            {"constraint": "FTR_PROBLEM_DONE", "edge": "PROBLEM_CORRECT_R"}, // if done with problem, continue to next problem
            {"constraint": "FTR_PROBLEM_HAS_MORE", "edge": "NEXT_DIGIT_R"}   // if not done, progress to next digit
          ]
        },

        "WRONG_FEEDBACK_R": {
          "COMMENT": "Provides feedback for wrong response.",
          "type": "node",
          "maptype": "moduleMap",
          "mapname": "WRONGFEEDBACK",
          "preenter": [],
          "preexit": [],
          "edges": [
            {"constraint": "", "edge": "USER_INPUT_R"} // go back to wait for user input
          ]
        },

        "PROBLEM_CORRECT_R": {
          "COMMENT": "When user has completed a problem.",
          "type": "node",
          "maptype": "moduleMap",
          "mapname": "PROBLEMCORRECT",
          "preenter": [],
          "preexit": [],
          "edges": [
            {"constraint": "FTR_MORE_PROBLEMS", "edge": "NEXT_PROBLEM"}, // if more problems, go to next problem
            {"constraint": "FTR_PROBLEMS_DONE", "edge": "NEXT_SCENE"}    // if problems done, go to next scene (aka finish)
          ]
        },

        // ==========================
        // ====== BEGIN CARRY  ======
        // ==========================

        "BEGIN_PROBLEM_CARRY": {
          "type": "NODE",
          "COMMENT": "Regular problem with no carry or borrow.",
          "maptype":"moduleMap",
          "mapname": "EMPTY",
          "preenter": [],
          "preexit": [],
          "edges": [
            {"constraint": "", "edge": "NEXT_DIGIT_C"}
          ]
        },

        // MATH_AG (c)
        // MATH_AG ONE_DIGIT_C
        // MATH_AG (c) TAP_THINGIES...
        // MATH_AG (c) "Write a one HERE... "
        // MATH_AG (s) sound files are here
        // MATH_AG (s) https://drive.google.com/drive/u/0/folders/1_ZaJmkW7rioIz7gIovIfdH6OQhgXyvQw
        "NEXT_DIGIT_C":{
          "COMMENT":"This node moves to the next digit in the problem.",
          "type":"node",
          "maptype":"moduleMap",
          "mapname": "NEXTDIGIT",
          "preenter":[],
          "preexit" :[],
          "edges":
          [
            {"constraint":"","edge":"USER_INPUT_C"}
          ]
        },

        "USER_INPUT_C": {
          "COMMENT":"Preps the tutor for user input, then waits for user input.",
          "type": "node",
          "maptype":"moduleMap",
          "mapname": "USERINPUT",
          "preenter": [],
          "preexit": [],
          "edges": [
            {"constraint": "FTR_CORRECT", "edge": "CORRECT_FEEDBACK_C"},
            {"constraint": "", "edge": "WRONG_FEEDBACK_C"}
          ]
        },

        "CORRECT_FEEDBACK_C": {
          "COMMENT": "Provides feedback for correct response.",
          "type": "node",
          "maptype": "moduleMap",
          "mapname": "CORRECTFEEDBACK",
          "preenter": [],
          "preexit": [],
          "edges": [
            {"constraint": "FTR_PROBLEM_DONE", "edge": "PROBLEM_CORRECT_C"}, // if done with problem, continue to next problem
            {"constraint": "FTR_PROBLEM_HAS_MORE", "edge": "NEXT_DIGIT_C"}   // if not done, progress to next digit
          ]
        },

        "WRONG_FEEDBACK_C": {
          "COMMENT": "Provides feedback for wrong response.",
          "type": "node",
          "maptype": "moduleMap",
          "mapname": "WRONGFEEDBACK",
          "preenter": [],
          "preexit": [],
          "edges": [
            {"constraint": "", "edge": "USER_INPUT_C"} // go back to wait for user input
          ]
        },

        "PROBLEM_CORRECT_C": {
          "COMMENT": "When user has completed a problem.",
          "type": "node",
          "maptype": "moduleMap",
          "mapname": "PROBLEMCORRECT",
          "preenter": [],
          "preexit": [],
          "edges": [
            {"constraint": "FTR_MORE_PROBLEMS", "edge": "NEXT_PROBLEM"}, // if more problems, go to next problem
            {"constraint": "FTR_PROBLEMS_DONE", "edge": "NEXT_SCENE"}    // if problems done, go to next scene (aka finish)
          ]
        },

        // ==========================
        // ====== BEGIN BORROW ======
        // ==========================

        "BEGIN_PROBLEM_BORROW": {
          "type": "NODE",
          "COMMENT": "Regular problem with no carry or borrow.",
          "maptype":"moduleMap",
          "mapname": "EMPTY",
          "preenter": [],
          "preexit": [],
          "edges": [
            {"constraint": "", "edge": "NEXT_DIGIT_ONE_B"}
          ]
        },

        // BORROW_AG (meta) These are the nodes in question
        "NEXT_DIGIT_ONE_B":{
          "COMMENT":"This node moves to the next digit in the problem.",
          "type":"node",
          "maptype":"moduleMap",
          "mapname": "NEXTDIGITONE_B",
          "preenter":[],
          "preexit" :[],
          "edges":
          [
            {"constraint": "FTR_ONE_DIGIT_WRITTEN","edge":"SCAFFOLDING_SHORTCUT_B"},
            {"constraint":"","edge":"TAP_TO_BORROW_B"}
          ]
        },

        // BORROW_AG (fix) "BORROW_TEN_AUDIO_B" plays too early... should wait to advance
        // BORROW_AG (meta) should these be here? Or could they be performed as one queue after another (triggered thru last method)
        // BORROW_AG (meta) then if the correct answer is written, it can CANCEL the queue and skip ahead to the CORRECT or WRONG...
        "TAP_TO_BORROW_B": {
          "COMMENT":"Wait for the user to tap to borrow.",
          "type":"node",
          "maptype":"moduleMap",
          "mapname": "BORROW_TEN_AUDIO_B", // BORROW_AG (node_ref) todo move good stuff here (what goes here???)
          "preenter":[],
          "preexit" :[],
          "edges":
          [
            {"constraint": "FTR_ONE_DIGIT_WRITTEN","edge":"SCAFFOLDING_SHORTCUT_B"},
            {"constraint":"","edge":"ONE_LESS_TEN_NODE_B"}
          ]
        },

        "ONE_LESS_TEN_NODE_B": {
          "COMMENT":"Cross out tens place and write one less.",
          "type":"node",
          "maptype":"moduleMap",
          "mapname": "ONE_LESS_TEN_B", // BORROW_AG (node_ref) todo move good stuff here
          "preenter":[],
          "preexit" :[],
          "edges":
          [
            {"constraint": "FTR_ONE_DIGIT_WRITTEN","edge":"SCAFFOLDING_SHORTCUT_B"},
            {"constraint":"","edge":"TEN_MORE_ONES_NODE_B"}
          ]
        },

        "TEN_MORE_ONES_NODE_B": {
          "COMMENT":"Cross out ones place and write ten more.",
          "type":"node",
          "maptype":"moduleMap",
          "mapname": "TEN_MORE_ONES_B", // BORROW_AG (node_ref) todo move good stuff here
          "preenter":[],
          "preexit" :[],
          "edges":
          [
            {"constraint": "FTR_ONE_DIGIT_WRITTEN","edge":"SCAFFOLDING_SHORTCUT_B"},
            {"constraint":"","edge":"USER_INPUT_ONE_B"}
          ]
        },

        "USER_INPUT_ONE_B": {
          "COMMENT":"Preps the tutor for user input, then waits for user input.",
          "type": "node",
          "maptype":"moduleMap",
          "mapname": "USERINPUT",
          "preenter": [],
          "preexit": [],
          "edges": [
            {"constraint": "FTR_CORRECT", "edge": "CORRECT_FEEDBACK_ONE_B"},
            {"constraint": "", "edge": "WRONG_FEEDBACK_ONE_B"}
          ]
        },

        "SCAFFOLDING_SHORTCUT_B": {
          "COMMENT": "If the student guesses before scaffolding is complete, this quickly completes all scaffolding steps.",
          "type": "node",
          "maptype":"moduleMap",
          "mapname": "SCAFFOLDINGSHORTCUT_B",
          "preenter": [],
          "preexit": [],
          "edges": [
            {"constraint": "FTR_CORRECT", "edge": "CORRECT_FEEDBACK_ONE_B"},
            {"constraint": "", "edge": "WRONG_FEEDBACK_ONE_B"}
          ]
        },

        "CORRECT_FEEDBACK_ONE_B": {
          "COMMENT": "Provides feedback for correct response.",
          "type": "node",
          "maptype": "moduleMap",
          "mapname": "CORRECTFEEDBACK",
          "preenter": [],
          "preexit": [],
          "edges": [
            {"constraint": "", "edge": "NEXT_DIGIT_TEN_B"}   // if not done, progress to next digit
          ]
        },

        "WRONG_FEEDBACK_ONE_B": {
          "COMMENT": "Provides feedback for wrong response.",
          "type": "node",
          "maptype": "moduleMap",
          "mapname": "WRONGFEEDBACK",
          "preenter": [],
          "preexit": [],
          "edges": [
            {"constraint": "", "edge": "USER_INPUT_ONE_B"} // go back to wait for user input
          ]
        },

        "NEXT_DIGIT_TEN_B":{
          "COMMENT":"This node moves to the next digit in the problem.",
          "type":"node",
          "maptype":"moduleMap",
          "mapname": "NEXTDIGITTEN_B",
          "preenter":[],
          "preexit" :[],
          "edges":
          [
            {"constraint":"","edge":"USER_INPUT_TEN_B"}
          ]
        },

        "USER_INPUT_TEN_B": {
          "COMMENT":"Preps the tutor for user input, then waits for user input.",
          "type": "node",
          "maptype":"moduleMap",
          "mapname": "USERINPUT",
          "preenter": [],
          "preexit": [],
          "edges": [
            {"constraint": "FTR_CORRECT", "edge": "CORRECT_FEEDBACK_TEN_B"},
            {"constraint": "", "edge": "WRONG_FEEDBACK_TEN_B"}
          ]
        },

        "CORRECT_FEEDBACK_TEN_B": {
          "COMMENT": "Provides feedback for correct response.",
          "type": "node",
          "maptype": "moduleMap",
          "mapname": "CORRECTFEEDBACK",
          "preenter": [],
          "preexit": [],
          "edges": [
            {"constraint": "FTR_PROBLEM_DONE", "edge": "PROBLEM_CORRECT_B"}, // if done with problem, continue to next problem
            {"constraint": "FTR_PROBLEM_HAS_MORE", "edge": "NEXT_DIGIT_ONE_B"}   // if not done, progress to next digit
          ]
        },

        "WRONG_FEEDBACK_TEN_B": {
          "COMMENT": "Provides feedback for wrong response.",
          "type": "node",
          "maptype": "moduleMap",
          "mapname": "WRONGFEEDBACK",
          "preenter": [],
          "preexit": [],
          "edges": [
            {"constraint": "", "edge": "USER_INPUT_TEN_B"} // go back to wait for user input
          ]
        },

        "PROBLEM_CORRECT_B": {
          "COMMENT": "When user has completed a problem.",
          "type": "node",
          "maptype": "moduleMap",
          "mapname": "PROBLEMCORRECT",
          "preenter": [],
          "preexit": [],
          "edges": [
            {"constraint": "FTR_MORE_PROBLEMS", "edge": "NEXT_PROBLEM"}, // if more problems, go to next problem
            {"constraint": "FTR_PROBLEMS_DONE", "edge": "NEXT_SCENE"}    // if problems done, go to next scene (aka finish)
          ]
        },

        // ======  NEXT_SCENE  ======
        "NEXT_SCENE": {
          "type": "NODE",
          "COMMENT": "When module is complete - move to next scene",
          "maptype": "actionMap",
          "mapname": "NEXTSCENE",
          "preenter": [],
          "preexit": [],
          "edges": [

          ]
        }

      },

      "moduleMap": {

        "COMMENT": "@@@@@  CModules  @@@@@",

        "INTRO": {
          "type": "MODULE",
          "reuse":true,
          "COMMENT": "???",
          "tracks": [
            {"name": "LOG_EVENT", "type": "QUEUEDCOMMAND", "id": "SBigMath", "method": "logState", "parms": "type#node,value#INTRO:String", "features":""},
            // welcome to math
            // TEMP
            {"name":"Introduction Audio", "type": "AUDIO", "command": "PLAY", "soundsource": "Lets add some numbers now.mp3",       "soundpackage":"temp", "volume": 1.0, "mode":"flow", "features": ""}
            ]
        },

        "NEXTPROBLEM": {
          "type": "MODULE",
          "reuse": true,
          "COMMENT": "???",
          "tracks": [
            {"name": "LOG_EVENT", "type": "QUEUEDCOMMAND", "id": "SBigMath", "method": "logState", "parms": "type#node,value#NEXTPROBLEM:String", "features":""},

            {"type": "COMMAND", "id": "SBigMath", "method": "next", "features": ""}
          ]
        },

        "EMPTY": {
          "type": "MODULE",
          "reuse": true,
          "COMMENT": "???",
          "tracks": [
            {"name": "LOG_EVENT", "type": "QUEUEDCOMMAND", "id": "SBigMath", "method": "logState", "parms": "type#node,value#EMPTY:String", "features":""}
          ]
        },

        "NEXTDIGIT": {
          "type": "MODULE",
          "reuse": true,
          "COMMENT": "???",
          "tracks": [
            {"name": "LOG_EVENT", "type": "QUEUEDCOMMAND", "id": "SBigMath", "method": "logState", "parms": "type#node,value#NEXTDIGITs:String", "features":""},
            {"type": "COMMAND", "id": "SBigMath", "method": "nextDigit", "features": ""},
            {"type": "AUDIO", "command": "PLAY", "soundsource": "Touch each one to add them up.mp3", "soundpackage":"bigmath", "volume": 1.0, "mode":"flow", "features": "FTR_ON_DIGIT_ONE"},
            {"type": "COMMAND", "id": "SBigMath", "method": "pointAtDotContainer", "parms": "opA:String|one:String", "features": "FTR_ON_DIGIT_ONE"},
            //{"type": "COMMAND", "id": "SBigMath", "method": "pointAtDigitInput", "parms": "result:String|one:String", "features": "FTR_ON_DIGIT_ONE"},
            {"type": "AUDIO", "command": "PLAY", "soundsource": "Touch each ten to add them up.mp3", "soundpackage":"bigmath", "volume": 1.0, "mode":"flow", "features": "FTR_ON_DIGIT_TEN"},
            {"type": "COMMAND", "id": "SBigMath", "method": "pointAtDotContainer", "parms": "opA:String|ten:String", "features": "FTR_ON_DIGIT_TEN"},
            //{"type": "COMMAND", "id": "SBigMath", "method": "pointAtDigitInput", "parms": "result:String|ten:String", "features": "FTR_ON_DIGIT_TEN"}

            {"type": "COMMAND", "id": "SBigMath", "method": "triggerHesitationTimer", "parms":"nextdigit:String", "features":""}

            // tap the numbers

          ]
        },


// MATH_BORROW (next) check to make sure we've borrowed... "lockOneDigitCorrect"
        // BORROW_AG (2) This is the first step of the nodes. make sure this is correct
        "NEXTDIGITONE_B": {
          "type": "MODULE",
          "reuse": true,
          "COMMENT": "???",
          "tracks": [
            {"name": "LOG_EVENT", "type": "QUEUEDCOMMAND", "id": "SBigMath", "method": "logState", "parms": "type#node,value#NEXTDIGITs:String", "features":""},
            {"type": "COMMAND", "id": "SBigMath", "method": "nextDigit", "features": ""},

            {"type": "COMMAND", "id": "SBigMath", "method": "lockOneDigitConcrete", "parms": "", "features": "FTR_ON_DIGIT_ONE"}, // lock digit
            {"type": "COMMAND", "id": "SBigMath", "method": "pointAtDotContainer", "parms": "opA:String|one:String", "features": "FTR_ON_DIGIT_ONE"},

            {"type": "AUDIO", "command": "PLAY", "soundsource": "Touch each one to take them away.mp3", "soundpackage":"bigmath", "volume": 1.0, "mode":"flow", "features": "FTR_ON_DIGIT_ONE"},

            //{"type": "COMMAND", "id": "SBigMath", "method": "pointAtDotContainer", "parms": "opA:String|ten:String", "features": "FTR_ON_DIGIT_ONE"},
            {"type": "COMMAND", "id": "SBigMath", "method": "triggerHesitationTimer", "parms":"nextdigineone_b:String", "features":""},
            {"type": "COMMAND", "cmd": "WAIT"} // BORROW_AG (advance) this is the key thing here... // BORROW_BUG something not happening...

            //{"type": "AUDIO", "command": "PLAY", "soundsource": "Touch each one to add them up.mp3", "soundpackage":"bigmath", "volume": 1.0, "mode":"flow", "features": "FTR_ON_DIGIT_ONE"},
            //{"type": "COMMAND", "id": "SBigMath", "method": "pointAtDotContainer", "parms": "opA:String|one:String", "features": "FTR_ON_DIGIT_ONE"},
            //{"type": "COMMAND", "id": "SBigMath", "method": "pointAtDigitInput", "parms": "result:String|one:String", "features": "FTR_ON_DIGIT_ONE"},
            //{"type": "AUDIO", "command": "PLAY", "soundsource": "Touch each ten to add them up.mp3", "soundpackage":"bigmath", "volume": 1.0, "mode":"flow", "features": "FTR_ON_DIGIT_TEN"},
            //{"type": "COMMAND", "id": "SBigMath", "method": "pointAtDotContainer", "parms": "opA:String|ten:String", "features": "FTR_ON_DIGIT_TEN"},
            //{"type": "COMMAND", "id": "SBigMath", "method": "pointAtDigitInput", "parms": "result:String|ten:String", "features": "FTR_ON_DIGIT_TEN"}



            // tap the numbers

          ]
        },

        "NEXTDIGITTEN_B": {
          "type": "MODULE",
          "reuse": true,
          "COMMENT": "???",
          "tracks": [
            {"name": "LOG_EVENT", "type": "QUEUEDCOMMAND", "id": "SBigMath", "method": "logState", "parms": "type#node,value#NEXTDIGITs:String", "features":""},
            {"type": "COMMAND", "id": "SBigMath", "method": "nextDigit", "features": ""},

            {"type": "COMMAND", "id": "SBigMath", "method": "lockOneDigitConcrete", "parms": "", "features": "FTR_ON_DIGIT_ONE"}, // lock digit
            {"type": "COMMAND", "id": "SBigMath", "method": "pointAtDotContainer", "parms": "opA:String|ten:String", "features": "FTR_ON_DIGIT_ONE"},
            // BORROW_AG (advance) this is the key thing here... // BORROW_BUG something not happening...

            //{"type": "AUDIO", "command": "PLAY", "soundsource": "Touch each one to add them up.mp3", "soundpackage":"bigmath", "volume": 1.0, "mode":"flow", "features": "FTR_ON_DIGIT_ONE"},
            //{"type": "COMMAND", "id": "SBigMath", "method": "pointAtDotContainer", "parms": "opA:String|one:String", "features": "FTR_ON_DIGIT_ONE"},
            //{"type": "COMMAND", "id": "SBigMath", "method": "pointAtDigitInput", "parms": "result:String|one:String", "features": "FTR_ON_DIGIT_ONE"},
            //{"type": "AUDIO", "command": "PLAY", "soundsource": "Touch each ten to add them up.mp3", "soundpackage":"bigmath", "volume": 1.0, "mode":"flow", "features": "FTR_ON_DIGIT_TEN"},
            {"type": "AUDIO", "command": "PLAY", "soundsource": "Touch each ten to take them away.mp3", "soundpackage":"bigmath", "volume": 1.0, "mode":"flow", "features": "FTR_ON_DIGIT_TEN"},
            {"type": "COMMAND", "id": "SBigMath", "method": "pointAtDotContainer", "parms": "opA:String|ten:String", "features": "FTR_ON_DIGIT_TEN"},
            //{"type": "COMMAND", "id": "SBigMath", "method": "pointAtDigitInput", "parms": "result:String|ten:String", "features": "FTR_ON_DIGIT_TEN"}

            {"type": "COMMAND", "id": "SBigMath", "method": "triggerHesitationTimer", "parms":"nextdigitten_b:String", "features":""}

            // tap the numbers

          ]
        },


        "USERINPUT": {
          "type": "MODULE",
          "reuse": true,
          "COMMENT": "???",
          "tracks": [
            {"name": "LOG_EVENT", "type": "QUEUEDCOMMAND", "id": "SBigMath", "method": "logState", "parms": "type#node,value#USERINPUT:String", "features":""},
            {"type": "COMMAND", "id": "SBigMath", "method": "triggerHesitationTimer", "parms":"userinput:String", "features":""},
            {"type": "COMMAND", "cmd": "WAIT"} // BORROW_AG (advance) this is the key thing here... // BORROW_BUG something not happening...
          ]
        },

        "CORRECTFEEDBACK": {
          "type": "MODULE",
          "reuse": true,
          "COMMENT": "???",
          "tracks": [
            {"name": "LOG_EVENT", "type": "QUEUEDCOMMAND", "id": "SBigMath", "method": "logState", "parms": "type#node,value#CORRECTFEEDBACK:String", "features":""},
            // Good!
            {"type": "AUDIO", "command": "PLAY", "soundsource": "Right.mp3", "soundpackage":"temp", "volume": 1.0, "mode":"flow", "features": ""}
          ]
        },

        "WRONGFEEDBACK": {
          "type": "MODULE",
          "reuse": true,
          "COMMENT": "???",
          "tracks": [
            {"name": "LOG_EVENT", "type": "QUEUEDCOMMAND", "id": "SBigMath", "method": "logState", "parms": "type#node,value#WRONGFEEDBACK:String", "features":""},

            {"type": "AUDIO", "command": "PLAY", "soundsource": "Not quite try again.mp3",       "soundpackage":"temp", "volume": 1.0, "mode":"flow", "features": ""},
            {"name": "LOG_EVENT", "type": "QUEUEDCOMMAND", "id": "SBigMath", "method": "eraseDigit", "parms":"{{SBigMath.digitToErase}}:String", "features":""}
          ]
        },

        "PROBLEMCORRECT": {
          "type": "MODULE",
          "reuse": true,
          "COMMENT": "???",
          "tracks": [
            {"name": "LOG_EVENT", "type": "QUEUEDCOMMAND", "id": "SBigMath", "method": "logState", "parms": "type#node,value#PROBLEMCORRECT:String", "features":""},
            {"name": "LOG_EVENT", "type": "QUEUEDCOMMAND", "id": "SBigMath", "method": "cancelHesitationTimer", "features":""},
            {"name": "LOG_EVENT", "type": "QUEUEDCOMMAND", "id": "SBigMath", "method": "highlightAll", "features":""},

            {"type": "AUDIO", "command": "PLAY", "soundsource": "Very good.mp3", "soundpackage":"temp", "volume": 1.0, "mode":"flow", "features": ""}
          ]
        },

        "SCAFFOLDINGSHORTCUT_B": {
          "type": "MODULE",
          "reuse": true,
          "COMMENT": "Wraps up all the scaffolding that hasn't been performed.",
          "preenter": [],
          "tracks": [
            {"name": "LOG_EVENT", "type": "QUEUEDCOMMAND", "id": "SBigMath", "method": "logState", "parms": "type#node,value#SCAFFOLDINGSHORTCUT_B:String", "features":""},
            {"name": "LOG_EVENT", "type": "QUEUEDCOMMAND", "id": "SBigMath", "method": "cancelHesitationTimer", "features":""},
            {"name": "LOG_EVENT", "type": "QUEUEDCOMMAND", "id": "SBigMath", "method": "wrapUpScaffolding", "features":""}
          ]
        },

        // BORROW_AG (node_ref) this should be in nodeMap
        "BORROW_TEN_AUDIO_B": {
          "type": "MODULE",
          "reuse": true,
          "COMMENT": "audio feedback for when you don't have enough ones",
          "preenter": [],
          "tracks": [
            {"name": "LOG_EVENT", "type": "QUEUEDCOMMAND", "id": "SBigMath", "method": "logState", "parms": "type#node,value#BORROW_TEN_AUDIO_B:String", "features":""},
            {"name": "LOG_EVENT", "type": "QUEUEDCOMMAND", "id": "SBigMath", "method": "cancelHesitationTimer", "features":""},
            {"type": "AUDIO", "command": "PLAY", "soundsource": "Here is a ten which we can trade for ten ones.mp3",  "soundpackage":"bigmath", "volume": 1.0, "mode":"flow", "features": "FTR_ON_DIGIT_ONE"}
          ]
        },

        // BORROW_AG (node_ref) this should be in nodeMap
        "ONE_LESS_TEN_B": {
          "type": "MODULE",
          "reuse": true,
          "COMMENT": "instructions for when you have one less ten",
          "preenter": [],
          "tracks": [
            {"name": "LOG_EVENT", "type": "QUEUEDCOMMAND", "id": "SBigMath", "method": "logState", "parms": "type#node,value#ONE_LESS_TEN_B:String", "features":""},
            {"name": "LOG_EVENT", "type": "QUEUEDCOMMAND", "id": "SBigMath", "method": "cancelHesitationTimer", "features":""},
            {"type": "COMMAND", "id": "SBigMath", "method": "oneLessTen", "parms": "", "features": "FTR_ON_DIGIT_ONE"},
            {"type": "COMMAND", "id": "SBigMath", "method": "pointAtDigitInput", "parms": "borrow:String|ten:String", "features": "FTR_ON_DIGIT_ONE"},
            {"type": "AUDIO", "command": "PLAY", "soundsource": "Now we have one less ten.mp3",  "soundpackage":"bigmath", "volume": 1.0, "mode":"flow", "features": "FTR_ON_DIGIT_ONE"}

          ]
        },

        // BORROW_AG (node_ref) this should be in nodeMap
        "TEN_MORE_ONES_B": {
          "type": "MODULE",
          "reuse": true,
          "COMMENT": "instructions for when you have one less ten",
          "preenter": [],
          "tracks": [
            {"name": "LOG_EVENT", "type": "QUEUEDCOMMAND", "id": "SBigMath", "method": "logState", "parms": "type#node,value#TEN_MORE_ONES_B:String", "features":""},
            {"name": "LOG_EVENT", "type": "QUEUEDCOMMAND", "id": "SBigMath", "method": "cancelHesitationTimer", "features":""},
            {"type": "COMMAND", "id": "SBigMath", "method": "tenMoreOnes", "parms": "", "features": "FTR_ON_DIGIT_ONE"},
            {"type": "COMMAND", "id": "SBigMath", "method": "pointAtDigitInput", "parms": "borrow:String|one:String", "features": "FTR_ON_DIGIT_ONE"},
            {"type": "AUDIO", "command": "PLAY", "soundsource": "Now we have ten more ones.mp3",  "soundpackage":"bigmath", "volume": 1.0, "mode":"flow", "features": "FTR_ON_DIGIT_ONE"},
            {"type": "COMMAND", "id": "SBigMath", "method": "triggerHesitationTimer", "parms": "ten_more_ones_b:String"}

          ]
        }

      },

      "actionMap": {

        "COMMENT": "@@@@@  CActions @@@@@ ",

        "SET_VERSION":{"type": "COMMAND", "id": "Sbanner", "method": "setVersionID", "parms": "v.0.0.1:String","features":""},

        "NEXTNODE": {"type": "COMMAND", "cmd": "NEXT"},

        "NEXTSCENE": {"type":"COMMAND", "cmd": "NEXTSCENE"}

      },

      "constraintMap": {

        "COMMENT": "@@@@@  CConstraints @@@@@ ",

        "FTR_IS_CARRY": {
          "type": "CONDITION",
          "test": "FTR_IS_CARRY"
        },

        "FTR_IS_BORROW": {
          "type": "CONDITION",
          "test": "FTR_IS_BORROW"
        },

        "FTR_CORRECT": {
          "type": "CONDITION",
          "test": "FTR_CORRECT"
        },

        "FTR_WRONG": {
          "type": "CONDITION",
          "test": "FTR_WRONG"
        },

        "FTR_ONE_DIGIT_WRITTEN": {
          "type": "CONDITION",
          "test": "FTR_ONE_DIGIT_WRITTEN"
        },

        "FTR_PROBLEM_DONE": {
          "type": "CONDITION",
          "test": "FTR_PROBLEM_DONE"
        },

        "FTR_PROBLEM_HAS_MORE": {
          "type": "CONDITION",
          "test": "FTR_PROBLEM_HAS_MORE"
        },

        "FTR_MORE_PROBLEMS": {
          "type": "CONDITION",
          "test": "FTR_MORE_PROBLEMS"
        },

        "FTR_PROBLEMS_DONE": {
          "type": "CONDITION",
          "test": "FTR_PROBLEMS_DONE"
        }

      }
    }
  }
}